LICENSE.txt
README.md
setup.cfg
setup.py
displaytree/__init__.py
displaytree/functions_binarytree.py
displaytree.egg-info/PKG-INFO
displaytree.egg-info/SOURCES.txt
displaytree.egg-info/dependency_links.txt
displaytree.egg-info/top_level.txt